app1/hello.py
lucasvieira_uv_publish_app1_test-0.1.0.dist-info/METADATA
lucasvieira_uv_publish_app1_test-0.1.0.dist-info/WHEEL
lucasvieira_uv_publish_app1_test-0.1.0.dist-info/RECORD
