Metadata-Version: 2.3
Name: lucasvieira-uv-publish-app1-test
Version: 0.1.0
Summary: Add your description here
Requires-Python: >=3.12
Requires-Dist: django>=5.1.4
Requires-Dist: fastapi[all,standard]>=0.115.6
Requires-Dist: lib1
